simple_sqlite/__init__.py
simple_sqlite/const.py
simple_sqlite/errors.py
simple_sqlite/main.py
py_simple_sqlite-1.1.0.dist-info/LICENSE
py_simple_sqlite-1.1.0.dist-info/METADATA
py_simple_sqlite-1.1.0.dist-info/WHEEL
py_simple_sqlite-1.1.0.dist-info/top_level.txt
py_simple_sqlite-1.1.0.dist-info/RECORD
